MANIFEST.in
README.md
requirements.txt
setup.py
apex_legends/__init__.py
apex_legends/base.py
apex_legends/domain.py
apex_legends/exceptions.py
apex_legends.egg-info/PKG-INFO
apex_legends.egg-info/SOURCES.txt
apex_legends.egg-info/dependency_links.txt
apex_legends.egg-info/pbr.json
apex_legends.egg-info/requires.txt
apex_legends.egg-info/top_level.txt