Metadata-Version: 2.1
Name: apex-legends
Version: 0.1.7
Summary: Python wrapper for https://apex.tracker.gg/ api.
Home-page: https://github.com/xcodinas/apex-legends
Author: Xavier Codinas
Author-email: xavier19966@gmail.com
License: MIT
Platform: UNKNOWN
Classifier: Development Status :: 3 - Alpha
Classifier: License :: OSI Approved :: MIT License
Classifier: Natural Language :: English
Classifier: Operating System :: OS Independent
Classifier: Programming Language :: Python :: 3
Classifier: Programming Language :: Python :: 3.6
Classifier: Topic :: Utilities
